Metadata-Version: 2.4
Name: asari-metabolomics-dev
Version: 1.15.dev6
Summary: LC-MS metabolomics data preprocessing
Home-page: https://github.com/shuzhao-li/asari
Author: J.Mitchell
Author-email: shuzhao.li@gmail.com
License: BSD 3-Clause
Keywords: metabolomics bioinformatics mass spectrometry TESTING
Classifier: Intended Audience :: Developers
Classifier: Intended Audience :: Science/Research
Classifier: License :: OSI Approved :: BSD License
Classifier: Natural Language :: English
Classifier: Operating System :: OS Independent
Classifier: Programming Language :: Python :: 3
Classifier: Topic :: Scientific/Engineering :: Bio-Informatics
Classifier: Topic :: Scientific/Engineering :: Chemistry
Classifier: Topic :: Software Development :: Libraries :: Python Modules
Requires-Python: >=3.7
License-File: LICENSE
Requires-Dist: metDatamodel
Requires-Dist: mass2chem
Requires-Dist: khipu-metabolomics>=0.7.0
Requires-Dist: jms-metabolite-services>=0.5.7
Requires-Dist: pymzml
Requires-Dist: numpy
Requires-Dist: scipy
Requires-Dist: statsmodels
Requires-Dist: pyyaml
Requires-Dist: panel>=0.13.0
Requires-Dist: holoviews
Requires-Dist: hvplot
Requires-Dist: seaborn
Requires-Dist: matplotlib
Requires-Dist: tqdm
Requires-Dist: json_tricks
Requires-Dist: plotly
Requires-Dist: matchms
Requires-Dist: pypdf
Dynamic: author
Dynamic: author-email
Dynamic: classifier
Dynamic: description
Dynamic: description-content-type
Dynamic: home-page
Dynamic: keywords
Dynamic: license
Dynamic: license-file
Dynamic: requires-dist
Dynamic: requires-python
Dynamic: summary
